<?xml version="1.0" encoding="utf-8"?>
<odoo>

    <!-- Real EState menu -->
    <menuitem id="estate_menu_root" name="Real Estate">
        <menuitem id="estate_first_level_menu" name="First_level">
            <menuitem id="estate_property_menu_action" action="estate_property_action"/>
        </menuitem>
    </menuitem>

    <!-- Types Item Settings menu (references estate_property_type_views.xml) -->
    <menuitem id="estate_type_menu_root" name="Estate Types">
        <menuitem id="estate_type_first_level_menu" name="Settings">
            <menuitem id="estate_property_type_menu_action" action="estate_property_type_action"/>
        </menuitem>
    </menuitem>

</odoo>